DFRobot/DAC.py
DFRobot/__init__.py
DFRobot_GP8403-10.0.0.dist-info/LICENSE
DFRobot_GP8403-10.0.0.dist-info/METADATA
DFRobot_GP8403-10.0.0.dist-info/WHEEL
DFRobot_GP8403-10.0.0.dist-info/top_level.txt
DFRobot_GP8403-10.0.0.dist-info/RECORD
